monologix/__init__.py
monologix/log.py
monologix-0.1.0.dist-info/METADATA
monologix-0.1.0.dist-info/WHEEL
monologix-0.1.0.dist-info/top_level.txt
monologix-0.1.0.dist-info/RECORD
