Metadata-Version: 2.2
Name: monologix
Version: 0.1.0
Summary: A library for logging and error handling
Requires-Python: <4.0,>=3.11
